pydivert/__init__.py
pydivert/consts.py
pydivert/util.py
pydivert/windivert.py
pydivert/packet/__init__.py
pydivert/packet/header.py
pydivert/packet/icmp.py
pydivert/packet/ip.py
pydivert/packet/tcp.py
pydivert/packet/udp.py
pydivert/tests/__init__.py
pydivert/tests/fixtures.py
pydivert/tests/test_packet.py
pydivert/tests/test_windivert.py
pydivert/windivert_dll/WinDivert32.dll
pydivert/windivert_dll/WinDivert32.sys
pydivert/windivert_dll/WinDivert64.dll
pydivert/windivert_dll/WinDivert64.sys
pydivert/windivert_dll/__init__.py
pydivert/windivert_dll/structs.py
pydivert-2.1.0.dist-info/DESCRIPTION.rst
pydivert-2.1.0.dist-info/LICENSE.txt
pydivert-2.1.0.dist-info/METADATA
pydivert-2.1.0.dist-info/RECORD
pydivert-2.1.0.dist-info/WHEEL
pydivert-2.1.0.dist-info/metadata.json
pydivert-2.1.0.dist-info/top_level.txt
