Metadata-Version: 1.1
Name: pydivert
Version: 2.1.0
Summary: Python binding to windivert driver
Home-page: https://github.com/ffalcinelli/pydivert
Author: Fabio Falcinelli
Author-email: fabio.falcinelli@gmail.com
License: LGPLv3
Download-URL: https://github.com/ffalcinelli/pydivert/releases/2.1.0
Keywords: windivert,network,tcp/ip
Platform: UNKNOWN
Classifier: Development Status :: 4 - Beta
Classifier: Environment :: Win32 (MS Windows)
Classifier: Intended Audience :: Developers
Classifier: Intended Audience :: System Administrators
Classifier: Intended Audience :: Telecommunications Industry
Classifier: License :: OSI Approved :: GNU Lesser General Public License v3 or later (LGPLv3+)
Classifier: Operating System :: Microsoft :: Windows :: Windows Vista
Classifier: Operating System :: Microsoft :: Windows :: Windows Server 2008
Classifier: Operating System :: Microsoft :: Windows :: Windows 7
Classifier: Programming Language :: Python
Classifier: Programming Language :: Python :: 2.7
Classifier: Programming Language :: Python :: 3.4
Classifier: Programming Language :: Python :: 3.5
Classifier: Programming Language :: Python :: 3.6
Classifier: Topic :: Software Development :: Libraries :: Python Modules
Classifier: Topic :: System :: Networking :: Firewalls
Classifier: Topic :: System :: Networking :: Monitoring
Classifier: Topic :: Utilities
